rethinkdb/_restore.py
rethinkdb/_export.py
rethinkdb/_compat.py
rethinkdb/ast.py
rethinkdb/_import.py
rethinkdb/_dump.py
rethinkdb/pbcpp.py
rethinkdb/net.py
rethinkdb/ql2_pb2.py
rethinkdb/__init__.py
rethinkdb/docs.py
rethinkdb/errors.py
rethinkdb/query.py
rethinkdb/repl.py
rethinkdb/_backup.py
rethinkdb_py3-0.2.dist-info/DESCRIPTION.rst
rethinkdb_py3-0.2.dist-info/top_level.txt
rethinkdb_py3-0.2.dist-info/METADATA
rethinkdb_py3-0.2.dist-info/WHEEL
rethinkdb_py3-0.2.dist-info/zip-safe
rethinkdb_py3-0.2.dist-info/entry_points.txt
rethinkdb_py3-0.2.dist-info/RECORD
rethinkdb_py3-0.2.dist-info/metadata.json
