Metadata-Version: 2.0
Name: rethinkdb-py3
Version: 0.2
Summary: Unofficial RethinkDB driver ported to Python 3
Home-page: http://rethinkdb.com/
Author: Barosl Lee
Author-email: UNKNOWN
License: UNKNOWN
Platform: UNKNOWN
